.DS_Store
ASDtools/ASDtools.py
ASDtools/__init__.py
ASDtools-0.4.0.dist-info/METADATA
ASDtools-0.4.0.dist-info/WHEEL
ASDtools-0.4.0.dist-info/top_level.txt
ASDtools-0.4.0.dist-info/RECORD
