Metadata-Version: 2.1
Name: ASDtools
Version: 0.4.0
Summary: A set of tools for loading and visualizing the NIST ASD.
Home-page: https://github.com/Autumn10677/ASDtools.git
Author: Autumn Stephens
Author-email: aust8150@colorado.edu
Requires-Dist: astropy
Requires-Dist: astroquery
Requires-Dist: Fraction
Requires-Dist: ipython!=8.17.1,<9.0.0,>=8.13.0
Requires-Dist: matplotlib
Requires-Dist: numpy<2
Requires-Dist: pandas
Requires-Dist: periodictable
Requires-Dist: roman
Requires-Dist: sympy
Requires-Dist: tqdm
